{
  "records": [
    {
      "size": 38,
      "seed": 0,
      "budget": 60,
      "steps_per_walk": 8,
      "proposal_relax_steps": 40,
      "algorithm": "ssw",
      "best_energy": -146.8714328243031,
      "energy_gap": 27.0569941756969,
      "success": false,
      "local_relaxations": 60,
      "force_evaluations": 36195,
      "budget_exhausted": false,
      "n_minima": 60,
      "duplicate_rate": 0.0,
      "frontier_nodes": 49,
      "dead_nodes": 0,
      "mean_node_duplicate_failure_rate": 0.0,
      "max_node_duplicate_failure_rate": 0.0,
      "direction_choices": 472,
      "direction_candidate_evaluations": 6077,
      "direction_mean_candidate_pool_size": 12.875,
      "direction_rigid_body_overlap_mean": 0.04872614091548837,
      "direction_post_projection_rigid_body_overlap_mean": 1.1993599271298733e-32,
      "direction_selected_soft": 413,
      "direction_selected_random": 59,
      "direction_selected_bond": 0,
      "direction_selected_cell": 0,
      "true_quench_count": 60,
      "true_quench_unconverged": 24,
      "true_quench_max_gradient": 1.9614233827416558,
      "true_quench_mean_iterations": 36.95,
      "proposal_relax_count": 472,
      "proposal_relax_unconverged": 471,
      "proposal_relax_max_gradient": 9.152644806205917,
      "proposal_relax_mean_iterations": 37.11228813559322
    },
    {
      "size": 38,
      "seed": 0,
      "budget": 60,
      "steps_per_walk": 8,
      "proposal_relax_steps": 80,
      "algorithm": "ssw",
      "best_energy": -169.48980241357506,
      "energy_gap": 4.438624586424936,
      "success": false,
      "local_relaxations": 60,
      "force_evaluations": 53794,
      "budget_exhausted": false,
      "n_minima": 60,
      "duplicate_rate": 0.0,
      "frontier_nodes": 39,
      "dead_nodes": 0,
      "mean_node_duplicate_failure_rate": 0.0,
      "max_node_duplicate_failure_rate": 0.0,
      "direction_choices": 472,
      "direction_candidate_evaluations": 6077,
      "direction_mean_candidate_pool_size": 12.875,
      "direction_rigid_body_overlap_mean": 0.06139869094502645,
      "direction_post_projection_rigid_body_overlap_mean": 3.535483083112673e-32,
      "direction_selected_soft": 413,
      "direction_selected_random": 59,
      "direction_selected_bond": 0,
      "direction_selected_cell": 0,
      "true_quench_count": 60,
      "true_quench_unconverged": 22,
      "true_quench_max_gradient": 1.8858081209178525,
      "true_quench_mean_iterations": 34.916666666666664,
      "proposal_relax_count": 472,
      "proposal_relax_unconverged": 385,
      "proposal_relax_max_gradient": 6.51337925295052,
      "proposal_relax_mean_iterations": 72.59745762711864
    },
    {
      "size": 38,
      "seed": 0,
      "budget": 60,
      "steps_per_walk": 14,
      "proposal_relax_steps": 40,
      "algorithm": "ssw",
      "best_energy": -169.48980238230396,
      "energy_gap": 4.438624617696036,
      "success": false,
      "local_relaxations": 60,
      "force_evaluations": 64039,
      "budget_exhausted": false,
      "n_minima": 60,
      "duplicate_rate": 0.0,
      "frontier_nodes": 32,
      "dead_nodes": 0,
      "mean_node_duplicate_failure_rate": 0.0,
      "max_node_duplicate_failure_rate": 0.0,
      "direction_choices": 826,
      "direction_candidate_evaluations": 10679,
      "direction_mean_candidate_pool_size": 12.928571428571429,
      "direction_rigid_body_overlap_mean": 0.06274558494449609,
      "direction_post_projection_rigid_body_overlap_mean": 8.98039526423146e-32,
      "direction_selected_soft": 767,
      "direction_selected_random": 59,
      "direction_selected_bond": 0,
      "direction_selected_cell": 0,
      "true_quench_count": 60,
      "true_quench_unconverged": 26,
      "true_quench_max_gradient": 1.8858081209178525,
      "true_quench_mean_iterations": 48.1,
      "proposal_relax_count": 826,
      "proposal_relax_unconverged": 822,
      "proposal_relax_max_gradient": 8.360001079438492,
      "proposal_relax_mean_iterations": 39.875302663438255
    },
    {
      "size": 38,
      "seed": 0,
      "budget": 60,
      "steps_per_walk": 14,
      "proposal_relax_steps": 80,
      "algorithm": "ssw",
      "best_energy": -167.70870437236937,
      "energy_gap": 6.219722627630631,
      "success": false,
      "local_relaxations": 60,
      "force_evaluations": 92784,
      "budget_exhausted": false,
      "n_minima": 60,
      "duplicate_rate": 0.0,
      "frontier_nodes": 27,
      "dead_nodes": 0,
      "mean_node_duplicate_failure_rate": 0.0,
      "max_node_duplicate_failure_rate": 0.0,
      "direction_choices": 826,
      "direction_candidate_evaluations": 10679,
      "direction_mean_candidate_pool_size": 12.928571428571429,
      "direction_rigid_body_overlap_mean": 0.06578232041903578,
      "direction_post_projection_rigid_body_overlap_mean": 1.0718483265864067e-31,
      "direction_selected_soft": 767,
      "direction_selected_random": 59,
      "direction_selected_bond": 0,
      "direction_selected_cell": 0,
      "true_quench_count": 60,
      "true_quench_unconverged": 23,
      "true_quench_max_gradient": 1.8858081209178525,
      "true_quench_mean_iterations": 46.6,
      "proposal_relax_count": 826,
      "proposal_relax_unconverged": 736,
      "proposal_relax_max_gradient": 6.950990294860805,
      "proposal_relax_mean_iterations": 73.2179176755448
    }
  ]
}